{
  "timestamp": 1770590165.1695528,
  "bots": {
    "bot_000": {
      "bot_id": "bot_000",
      "pid": 31250,
      "config": "config/swarm_demo/bot_01.yaml",
      "state": "completed",
      "sector": 591,
      "credits": 221391,
      "turns_executed": 500,
      "turns_max": 500,
      "uptime_seconds": 0,
      "last_update_time": 1770588842.459954,
      "completed_at": 1770588845.183135,
      "error_message": null,
      "last_action": "BANK",
      "last_action_time": 1770588842.258467,
      "activity_context": "FINISHED",
      "error_type": null,
      "error_timestamp": null,
      "exit_reason": "target_reached",
      "recent_actions": [
        {
          "time": 1770588840.193024,
          "action": "BANK",
          "sector": 591,
          "details": null,
          "result": "success"
        },
        {
          "time": 1770588840.422483,
          "action": "BANK",
          "sector": 591,
          "details": null,
          "result": "success"
        },
        {
          "time": 1770588840.651627,
          "action": "BANK",
          "sector": 591,
          "details": null,
          "result": "success"
        },
        {
          "time": 1770588840.881033,
          "action": "BANK",
          "sector": 591,
          "details": null,
          "result": "success"
        },
        {
          "time": 1770588841.112484,
          "action": "BANK",
          "sector": 591,
          "details": null,
          "result": "success"
        },
        {
          "time": 1770588841.341258,
          "action": "BANK",
          "sector": 591,
          "details": null,
          "result": "success"
        },
        {
          "time": 1770588841.5711172,
          "action": "BANK",
          "sector": 591,
          "details": null,
          "result": "success"
        },
        {
          "time": 1770588841.801881,
          "action": "BANK",
          "sector": 591,
          "details": null,
          "result": "success"
        },
        {
          "time": 1770588842.0305028,
          "action": "BANK",
          "sector": 591,
          "details": null,
          "result": "success"
        },
        {
          "time": 1770588842.25848,
          "action": "BANK",
          "sector": 591,
          "details": null,
          "result": "success"
        }
      ],
      "username": "bot_000",
      "ship_name": null,
      "ship_level": null,
      "port_location": null
    },
    "bot_001": {
      "bot_id": "bot_001",
      "pid": 31251,
      "config": "config/swarm_demo/bot_02.yaml",
      "state": "completed",
      "sector": 56,
      "credits": 221391,
      "turns_executed": 14,
      "turns_max": 500,
      "uptime_seconds": 0,
      "last_update_time": 1770588820.3402932,
      "completed_at": 1770588825.180704,
      "error_message": "No heartbeat in 60s - bot process may have crashed or is stuck",
      "last_action": "EXPLORE",
      "last_action_time": 1770588798.7669692,
      "activity_context": "FINISHED",
      "error_type": "HeartbeatTimeout",
      "error_timestamp": 1770588755.1757572,
      "exit_reason": "target_reached",
      "recent_actions": [
        {
          "time": 1770588793.343703,
          "action": "TRADE",
          "sector": 591,
          "details": "all_commodities",
          "result": "failure"
        },
        {
          "time": 1770588796.1239412,
          "action": "TRADE",
          "sector": 591,
          "details": "all_commodities",
          "result": "failure"
        },
        {
          "time": 1770588798.536105,
          "action": "WAIT",
          "sector": 591,
          "details": null,
          "result": "success"
        },
        {
          "time": 1770588804.644477,
          "action": "EXPLORE",
          "sector": 56,
          "details": "591",
          "result": "failure"
        }
      ],
      "username": "bot_001",
      "ship_name": null,
      "ship_level": null,
      "port_location": null
    },
    "bot_002": {
      "bot_id": "bot_002",
      "pid": 31459,
      "config": "config/swarm_demo/bot_01.yaml",
      "state": "completed",
      "sector": 56,
      "credits": 221391,
      "turns_executed": 500,
      "turns_max": 500,
      "uptime_seconds": 0,
      "last_update_time": 1770588911.627945,
      "completed_at": 1770588915.188687,
      "error_message": null,
      "last_action": "BANK",
      "last_action_time": 1770588908.441441,
      "activity_context": "FINISHED",
      "error_type": null,
      "error_timestamp": null,
      "exit_reason": "target_reached",
      "recent_actions": [
        {
          "time": 1770588906.37606,
          "action": "BANK",
          "sector": 56,
          "details": null,
          "result": "success"
        },
        {
          "time": 1770588906.605976,
          "action": "BANK",
          "sector": 56,
          "details": null,
          "result": "success"
        },
        {
          "time": 1770588906.835818,
          "action": "BANK",
          "sector": 56,
          "details": null,
          "result": "success"
        },
        {
          "time": 1770588907.064977,
          "action": "BANK",
          "sector": 56,
          "details": null,
          "result": "success"
        },
        {
          "time": 1770588907.2943518,
          "action": "BANK",
          "sector": 56,
          "details": null,
          "result": "success"
        },
        {
          "time": 1770588907.524056,
          "action": "BANK",
          "sector": 56,
          "details": null,
          "result": "success"
        },
        {
          "time": 1770588907.7535958,
          "action": "BANK",
          "sector": 56,
          "details": null,
          "result": "success"
        },
        {
          "time": 1770588907.982889,
          "action": "BANK",
          "sector": 56,
          "details": null,
          "result": "success"
        },
        {
          "time": 1770588908.212516,
          "action": "BANK",
          "sector": 56,
          "details": null,
          "result": "success"
        },
        {
          "time": 1770588908.4414542,
          "action": "BANK",
          "sector": 56,
          "details": null,
          "result": "success"
        }
      ],
      "username": "bot_002",
      "ship_name": null,
      "ship_level": null,
      "port_location": null
    },
    "bot_003": {
      "bot_id": "bot_003",
      "pid": 31460,
      "config": "config/swarm_demo/bot_02.yaml",
      "state": "completed",
      "sector": 567,
      "credits": 232911,
      "turns_executed": 282,
      "turns_max": 500,
      "uptime_seconds": 0,
      "last_update_time": 1770590067.98577,
      "completed_at": 1770590075.276617,
      "error_message": null,
      "last_action": "TRADE",
      "last_action_time": 1770589971.2155252,
      "activity_context": "FINISHED",
      "error_type": null,
      "error_timestamp": null,
      "exit_reason": "target_reached",
      "recent_actions": [
        {
          "time": 1770589743.305027,
          "action": "EXPLORE",
          "sector": 567,
          "details": "126",
          "result": "success"
        },
        {
          "time": 1770589750.573246,
          "action": "EXPLORE",
          "sector": 567,
          "details": "567",
          "result": "failure"
        },
        {
          "time": 1770589817.50192,
          "action": "TRADE",
          "sector": 567,
          "details": "all_commodities",
          "result": "failure"
        },
        {
          "time": 1770589884.5290902,
          "action": "TRADE",
          "sector": 567,
          "details": "all_commodities",
          "result": "failure"
        },
        {
          "time": 1770589886.2926989,
          "action": "EXPLORE",
          "sector": 567,
          "details": "498",
          "result": "success"
        },
        {
          "time": 1770589890.240743,
          "action": "EXPLORE",
          "sector": 567,
          "details": "126",
          "result": "success"
        },
        {
          "time": 1770589894.1868281,
          "action": "EXPLORE",
          "sector": 567,
          "details": "126",
          "result": "success"
        },
        {
          "time": 1770589903.948417,
          "action": "EXPLORE",
          "sector": 498,
          "details": "567",
          "result": "failure"
        },
        {
          "time": 1770589970.987277,
          "action": "TRADE",
          "sector": 567,
          "details": "all_commodities",
          "result": "failure"
        },
        {
          "time": 1770590038.6185448,
          "action": "TRADE",
          "sector": 567,
          "details": "all_commodities",
          "result": "failure"
        }
      ],
      "username": "bot_003",
      "ship_name": null,
      "ship_level": null,
      "port_location": null
    },
    "bot_004": {
      "bot_id": "bot_004",
      "pid": 31461,
      "config": "config/swarm_demo/bot_03.yaml",
      "state": "completed",
      "sector": 0,
      "credits": 0,
      "turns_executed": 0,
      "turns_max": 500,
      "uptime_seconds": 0,
      "last_update_time": 1770588868.120286,
      "completed_at": 1770588875.185351,
      "error_message": "No prompt detected within 90000ms",
      "last_action": null,
      "last_action_time": 0,
      "activity_context": "FINISHED",
      "error_type": "TimeoutError",
      "error_timestamp": 1770588868.114686,
      "exit_reason": "target_reached",
      "recent_actions": [],
      "username": null,
      "ship_name": null,
      "ship_level": null,
      "port_location": null
    },
    "bot_005": {
      "bot_id": "bot_005",
      "pid": 31462,
      "config": "config/swarm_demo/bot_04.yaml",
      "state": "completed",
      "sector": 0,
      "credits": 0,
      "turns_executed": 0,
      "turns_max": 500,
      "uptime_seconds": 0,
      "last_update_time": 1770588867.307999,
      "completed_at": 1770588875.1858099,
      "error_message": "No prompt detected within 90000ms",
      "last_action": null,
      "last_action_time": 0,
      "activity_context": "FINISHED",
      "error_type": "TimeoutError",
      "error_timestamp": 1770588867.301953,
      "exit_reason": "target_reached",
      "recent_actions": [],
      "username": null,
      "ship_name": null,
      "ship_level": null,
      "port_location": null
    },
    "bot_006": {
      "bot_id": "bot_006",
      "pid": 31463,
      "config": "config/swarm_demo/bot_05.yaml",
      "state": "completed",
      "sector": 0,
      "credits": 0,
      "turns_executed": 0,
      "turns_max": 500,
      "uptime_seconds": 0,
      "last_update_time": 1770588867.30702,
      "completed_at": 1770588875.186286,
      "error_message": "No prompt detected within 90000ms",
      "last_action": null,
      "last_action_time": 0,
      "activity_context": "FINISHED",
      "error_type": "TimeoutError",
      "error_timestamp": 1770588867.301705,
      "exit_reason": "target_reached",
      "recent_actions": [],
      "username": null,
      "ship_name": null,
      "ship_level": null,
      "port_location": null
    },
    "bot_007": {
      "bot_id": "bot_007",
      "pid": 31665,
      "config": "config/swarm_demo_ai/bot_01.yaml",
      "state": "error",
      "sector": 0,
      "credits": 0,
      "turns_executed": 0,
      "turns_max": 500,
      "uptime_seconds": 0,
      "last_update_time": 1770588786.7516139,
      "completed_at": null,
      "error_message": "Process exited with code 1",
      "last_action": null,
      "last_action_time": 0,
      "activity_context": null,
      "error_type": null,
      "error_timestamp": null,
      "exit_reason": "exit_code_1",
      "recent_actions": [],
      "username": null,
      "ship_name": null,
      "ship_level": null,
      "port_location": null
    }
  }
}