{
  "timestamp": 1770523671.558133,
  "bots": {
    "bot_02_game_B_opportunistic": {
      "bot_id": "bot_02_game_B_opportunistic",
      "pid": 6282,
      "config": "config/test_matrix/02_game_B_opportunistic.yaml",
      "state": "completed",
      "sector": 0,
      "credits": 0,
      "turns_executed": 0,
      "uptime_seconds": 0,
      "last_update_time": 1770521497.576253,
      "error_message": null
    },
    "bot_02_gameA_opp_t15_e2_b0": {
      "bot_id": "bot_02_gameA_opp_t15_e2_b0",
      "pid": 6286,
      "config": "config/test_matrix/02_gameA_opp_t15_e2_b0.yaml",
      "state": "completed",
      "sector": 0,
      "credits": 0,
      "turns_executed": 0,
      "uptime_seconds": 0,
      "last_update_time": 1770521509.504878,
      "error_message": null
    },
    "bot_03_game_C_ai_basic": {
      "bot_id": "bot_03_game_C_ai_basic",
      "pid": 6290,
      "config": "config/test_matrix/03_game_C_ai_basic.yaml",
      "state": "completed",
      "sector": 0,
      "credits": 0,
      "turns_executed": 0,
      "uptime_seconds": 0,
      "last_update_time": 1770521481.921761,
      "error_message": null
    },
    "bot_03_gameA_opp_t15_e5_b1": {
      "bot_id": "bot_03_gameA_opp_t15_e5_b1",
      "pid": 6294,
      "config": "config/test_matrix/03_gameA_opp_t15_e5_b1.yaml",
      "state": "completed",
      "sector": 0,
      "credits": 0,
      "turns_executed": 0,
      "uptime_seconds": 0,
      "last_update_time": 1770521510.158098,
      "error_message": null
    },
    "bot_04_gameA_opp_t15_e5_b0": {
      "bot_id": "bot_04_gameA_opp_t15_e5_b0",
      "pid": 6298,
      "config": "config/test_matrix/04_gameA_opp_t15_e5_b0.yaml",
      "state": "completed",
      "sector": 0,
      "credits": 0,
      "turns_executed": 0,
      "uptime_seconds": 0,
      "last_update_time": 1770521510.1999161,
      "error_message": null
    },
    "bot_05_gameA_opp_t15_e8_b1": {
      "bot_id": "bot_05_gameA_opp_t15_e8_b1",
      "pid": 6302,
      "config": "config/test_matrix/05_gameA_opp_t15_e8_b1.yaml",
      "state": "completed",
      "sector": 0,
      "credits": 0,
      "turns_executed": 0,
      "uptime_seconds": 0,
      "last_update_time": 1770521481.924107,
      "error_message": null
    },
    "bot_06_gameA_opp_t15_e8_b0": {
      "bot_id": "bot_06_gameA_opp_t15_e8_b0",
      "pid": 6306,
      "config": "config/test_matrix/06_gameA_opp_t15_e8_b0.yaml",
      "state": "completed",
      "sector": 0,
      "credits": 0,
      "turns_executed": 0,
      "uptime_seconds": 0,
      "last_update_time": 1770521510.1839318,
      "error_message": null
    },
    "bot_07_gameA_opp_t30_e2_b1": {
      "bot_id": "bot_07_gameA_opp_t30_e2_b1",
      "pid": 6310,
      "config": "config/test_matrix/07_gameA_opp_t30_e2_b1.yaml",
      "state": "completed",
      "sector": 0,
      "credits": 0,
      "turns_executed": 0,
      "uptime_seconds": 0,
      "last_update_time": 1770521495.400666,
      "error_message": null
    },
    "bot_08_gameA_opp_t30_e2_b0": {
      "bot_id": "bot_08_gameA_opp_t30_e2_b0",
      "pid": 6314,
      "config": "config/test_matrix/08_gameA_opp_t30_e2_b0.yaml",
      "state": "completed",
      "sector": 0,
      "credits": 0,
      "turns_executed": 0,
      "uptime_seconds": 0,
      "last_update_time": 1770521512.602731,
      "error_message": null
    },
    "bot_09_gameA_opp_t30_e5_b1": {
      "bot_id": "bot_09_gameA_opp_t30_e5_b1",
      "pid": 6318,
      "config": "config/test_matrix/09_gameA_opp_t30_e5_b1.yaml",
      "state": "completed",
      "sector": 0,
      "credits": 0,
      "turns_executed": 0,
      "uptime_seconds": 0,
      "last_update_time": 1770521482.801704,
      "error_message": null
    },
    "bot_10_gameA_opp_t30_e5_b0": {
      "bot_id": "bot_10_gameA_opp_t30_e5_b0",
      "pid": 6322,
      "config": "config/test_matrix/10_gameA_opp_t30_e5_b0.yaml",
      "state": "completed",
      "sector": 0,
      "credits": 0,
      "turns_executed": 0,
      "uptime_seconds": 0,
      "last_update_time": 1770521496.6390688,
      "error_message": null
    },
    "bot_100_gameC_ai_t30_int_auto0_b0": {
      "bot_id": "bot_100_gameC_ai_t30_int_auto0_b0",
      "pid": 6327,
      "config": "config/test_matrix/100_gameC_ai_t30_int_auto0_b0.yaml",
      "state": "completed",
      "sector": 0,
      "credits": 0,
      "turns_executed": 0,
      "uptime_seconds": 0,
      "last_update_time": 1770521482.905427,
      "error_message": null
    },
    "bot_101_gameC_ai_t30_int_auto1_b1": {
      "bot_id": "bot_101_gameC_ai_t30_int_auto1_b1",
      "pid": 6331,
      "config": "config/test_matrix/101_gameC_ai_t30_int_auto1_b1.yaml",
      "state": "completed",
      "sector": 0,
      "credits": 0,
      "turns_executed": 0,
      "uptime_seconds": 0,
      "last_update_time": 1770521510.0327308,
      "error_message": null
    },
    "bot_102_gameC_ai_t30_int_auto1_b0": {
      "bot_id": "bot_102_gameC_ai_t30_int_auto1_b0",
      "pid": 6337,
      "config": "config/test_matrix/102_gameC_ai_t30_int_auto1_b0.yaml",
      "state": "completed",
      "sector": 0,
      "credits": 0,
      "turns_executed": 0,
      "uptime_seconds": 0,
      "last_update_time": 1770521482.9051259,
      "error_message": null
    },
    "bot_103_gameC_ai_t50_no_int_b1": {
      "bot_id": "bot_103_gameC_ai_t50_no_int_b1",
      "pid": 6343,
      "config": "config/test_matrix/103_gameC_ai_t50_no_int_b1.yaml",
      "state": "completed",
      "sector": 0,
      "credits": 0,
      "turns_executed": 0,
      "uptime_seconds": 0,
      "last_update_time": 1770521510.358423,
      "error_message": null
    },
    "bot_104_gameC_ai_t50_no_int_b0": {
      "bot_id": "bot_104_gameC_ai_t50_no_int_b0",
      "pid": 6347,
      "config": "config/test_matrix/104_gameC_ai_t50_no_int_b0.yaml",
      "state": "completed",
      "sector": 0,
      "credits": 0,
      "turns_executed": 0,
      "uptime_seconds": 0,
      "last_update_time": 1770521482.902106,
      "error_message": null
    },
    "bot_105_gameC_ai_t50_int_auto0_b1": {
      "bot_id": "bot_105_gameC_ai_t50_int_auto0_b1",
      "pid": 6351,
      "config": "config/test_matrix/105_gameC_ai_t50_int_auto0_b1.yaml",
      "state": "completed",
      "sector": 0,
      "credits": 0,
      "turns_executed": 0,
      "uptime_seconds": 0,
      "last_update_time": 1770521483.2337222,
      "error_message": null
    },
    "bot_106_gameC_ai_t50_int_auto0_b0": {
      "bot_id": "bot_106_gameC_ai_t50_int_auto0_b0",
      "pid": 6355,
      "config": "config/test_matrix/106_gameC_ai_t50_int_auto0_b0.yaml",
      "state": "completed",
      "sector": 0,
      "credits": 0,
      "turns_executed": 0,
      "uptime_seconds": 0,
      "last_update_time": 1770521512.564076,
      "error_message": null
    },
    "bot_107_gameC_ai_t50_int_auto1_b1": {
      "bot_id": "bot_107_gameC_ai_t50_int_auto1_b1",
      "pid": 6359,
      "config": "config/test_matrix/107_gameC_ai_t50_int_auto1_b1.yaml",
      "state": "completed",
      "sector": 0,
      "credits": 0,
      "turns_executed": 0,
      "uptime_seconds": 0,
      "last_update_time": 1770521483.341365,
      "error_message": null
    },
    "bot_108_gameC_ai_t50_int_auto1_b0": {
      "bot_id": "bot_108_gameC_ai_t50_int_auto1_b0",
      "pid": 6364,
      "config": "config/test_matrix/108_gameC_ai_t50_int_auto1_b0.yaml",
      "state": "completed",
      "sector": 0,
      "credits": 0,
      "turns_executed": 0,
      "uptime_seconds": 0,
      "last_update_time": 1770521483.226437,
      "error_message": null
    },
    "bot_11_gameA_opp_t30_e8_b1": {
      "bot_id": "bot_11_gameA_opp_t30_e8_b1",
      "pid": 6369,
      "config": "config/test_matrix/11_gameA_opp_t30_e8_b1.yaml",
      "state": "completed",
      "sector": 0,
      "credits": 0,
      "turns_executed": 0,
      "uptime_seconds": 0,
      "last_update_time": 1770521483.341992,
      "error_message": null
    },
    "bot_12_gameA_opp_t30_e8_b0": {
      "bot_id": "bot_12_gameA_opp_t30_e8_b0",
      "pid": 6374,
      "config": "config/test_matrix/12_gameA_opp_t30_e8_b0.yaml",
      "state": "completed",
      "sector": 0,
      "credits": 0,
      "turns_executed": 0,
      "uptime_seconds": 0,
      "last_update_time": 1770521483.29003,
      "error_message": null
    },
    "bot_13_gameA_opp_t50_e2_b1": {
      "bot_id": "bot_13_gameA_opp_t50_e2_b1",
      "pid": 6379,
      "config": "config/test_matrix/13_gameA_opp_t50_e2_b1.yaml",
      "state": "completed",
      "sector": 0,
      "credits": 0,
      "turns_executed": 0,
      "uptime_seconds": 0,
      "last_update_time": 1770521483.3407528,
      "error_message": null
    },
    "bot_14_gameA_opp_t50_e2_b0": {
      "bot_id": "bot_14_gameA_opp_t50_e2_b0",
      "pid": 6384,
      "config": "config/test_matrix/14_gameA_opp_t50_e2_b0.yaml",
      "state": "completed",
      "sector": 0,
      "credits": 0,
      "turns_executed": 0,
      "uptime_seconds": 0,
      "last_update_time": 1770521483.348094,
      "error_message": null
    },
    "bot_15_gameA_opp_t50_e5_b1": {
      "bot_id": "bot_15_gameA_opp_t50_e5_b1",
      "pid": 6388,
      "config": "config/test_matrix/15_gameA_opp_t50_e5_b1.yaml",
      "state": "completed",
      "sector": 0,
      "credits": 0,
      "turns_executed": 0,
      "uptime_seconds": 0,
      "last_update_time": 1770521483.3453262,
      "error_message": null
    },
    "bot_16_gameA_opp_t50_e5_b0": {
      "bot_id": "bot_16_gameA_opp_t50_e5_b0",
      "pid": 6392,
      "config": "config/test_matrix/16_gameA_opp_t50_e5_b0.yaml",
      "state": "completed",
      "sector": 0,
      "credits": 0,
      "turns_executed": 0,
      "uptime_seconds": 0,
      "last_update_time": 1770521510.7830431,
      "error_message": null
    },
    "bot_17_gameA_opp_t50_e8_b1": {
      "bot_id": "bot_17_gameA_opp_t50_e8_b1",
      "pid": 6396,
      "config": "config/test_matrix/17_gameA_opp_t50_e8_b1.yaml",
      "state": "completed",
      "sector": 0,
      "credits": 0,
      "turns_executed": 0,
      "uptime_seconds": 0,
      "last_update_time": 1770521483.330878,
      "error_message": null
    },
    "bot_18_gameA_opp_t50_e8_b0": {
      "bot_id": "bot_18_gameA_opp_t50_e8_b0",
      "pid": 6400,
      "config": "config/test_matrix/18_gameA_opp_t50_e8_b0.yaml",
      "state": "completed",
      "sector": 0,
      "credits": 0,
      "turns_executed": 0,
      "uptime_seconds": 0,
      "last_update_time": 1770521483.5216472,
      "error_message": null
    },
    "bot_19_gameB_opp_t15_e2_b1": {
      "bot_id": "bot_19_gameB_opp_t15_e2_b1",
      "pid": 6404,
      "config": "config/test_matrix/19_gameB_opp_t15_e2_b1.yaml",
      "state": "completed",
      "sector": 0,
      "credits": 0,
      "turns_executed": 0,
      "uptime_seconds": 0,
      "last_update_time": 1770521483.505051,
      "error_message": null
    },
    "bot_20_gameB_opp_t15_e2_b0": {
      "bot_id": "bot_20_gameB_opp_t15_e2_b0",
      "pid": 6408,
      "config": "config/test_matrix/20_gameB_opp_t15_e2_b0.yaml",
      "state": "completed",
      "sector": 0,
      "credits": 0,
      "turns_executed": 0,
      "uptime_seconds": 0,
      "last_update_time": 1770521483.57759,
      "error_message": null
    },
    "bot_21_gameB_opp_t15_e5_b1": {
      "bot_id": "bot_21_gameB_opp_t15_e5_b1",
      "pid": 6412,
      "config": "config/test_matrix/21_gameB_opp_t15_e5_b1.yaml",
      "state": "completed",
      "sector": 228,
      "credits": 997,
      "turns_executed": 15,
      "uptime_seconds": 0,
      "last_update_time": 1770521572.797072,
      "error_message": null
    },
    "bot_22_gameB_opp_t15_e5_b0": {
      "bot_id": "bot_22_gameB_opp_t15_e5_b0",
      "pid": 6416,
      "config": "config/test_matrix/22_gameB_opp_t15_e5_b0.yaml",
      "state": "completed",
      "sector": 0,
      "credits": 0,
      "turns_executed": 0,
      "uptime_seconds": 0,
      "last_update_time": 1770521483.659699,
      "error_message": null
    },
    "bot_23_gameB_opp_t15_e8_b1": {
      "bot_id": "bot_23_gameB_opp_t15_e8_b1",
      "pid": 6420,
      "config": "config/test_matrix/23_gameB_opp_t15_e8_b1.yaml",
      "state": "completed",
      "sector": 0,
      "credits": 0,
      "turns_executed": 0,
      "uptime_seconds": 0,
      "last_update_time": 1770521483.639883,
      "error_message": null
    },
    "bot_24_gameB_opp_t15_e8_b0": {
      "bot_id": "bot_24_gameB_opp_t15_e8_b0",
      "pid": 6424,
      "config": "config/test_matrix/24_gameB_opp_t15_e8_b0.yaml",
      "state": "completed",
      "sector": 228,
      "credits": 997,
      "turns_executed": 15,
      "uptime_seconds": 0,
      "last_update_time": 1770521567.9686651,
      "error_message": null
    },
    "bot_25_gameB_opp_t30_e2_b1": {
      "bot_id": "bot_25_gameB_opp_t30_e2_b1",
      "pid": 6428,
      "config": "config/test_matrix/25_gameB_opp_t30_e2_b1.yaml",
      "state": "completed",
      "sector": 487,
      "credits": 997,
      "turns_executed": 30,
      "uptime_seconds": 0,
      "last_update_time": 1770521639.68793,
      "error_message": null
    },
    "bot_26_gameB_opp_t30_e2_b0": {
      "bot_id": "bot_26_gameB_opp_t30_e2_b0",
      "pid": 6433,
      "config": "config/test_matrix/26_gameB_opp_t30_e2_b0.yaml",
      "state": "completed",
      "sector": 836,
      "credits": 2122,
      "turns_executed": 30,
      "uptime_seconds": 0,
      "last_update_time": 1770521680.3117309,
      "error_message": null
    },
    "bot_27_gameB_opp_t30_e5_b1": {
      "bot_id": "bot_27_gameB_opp_t30_e5_b1",
      "pid": 6440,
      "config": "config/test_matrix/27_gameB_opp_t30_e5_b1.yaml",
      "state": "completed",
      "sector": 836,
      "credits": 2122,
      "turns_executed": 30,
      "uptime_seconds": 0,
      "last_update_time": 1770521674.914698,
      "error_message": null
    },
    "bot_28_gameB_opp_t30_e5_b0": {
      "bot_id": "bot_28_gameB_opp_t30_e5_b0",
      "pid": 6446,
      "config": "config/test_matrix/28_gameB_opp_t30_e5_b0.yaml",
      "state": "completed",
      "sector": 0,
      "credits": 0,
      "turns_executed": 0,
      "uptime_seconds": 0,
      "last_update_time": 1770521483.788571,
      "error_message": null
    },
    "bot_29_gameB_opp_t30_e8_b1": {
      "bot_id": "bot_29_gameB_opp_t30_e8_b1",
      "pid": 6452,
      "config": "config/test_matrix/29_gameB_opp_t30_e8_b1.yaml",
      "state": "completed",
      "sector": 0,
      "credits": 0,
      "turns_executed": 0,
      "uptime_seconds": 0,
      "last_update_time": 1770521483.577198,
      "error_message": null
    },
    "bot_30_gameB_opp_t30_e8_b0": {
      "bot_id": "bot_30_gameB_opp_t30_e8_b0",
      "pid": 6459,
      "config": "config/test_matrix/30_gameB_opp_t30_e8_b0.yaml",
      "state": "completed",
      "sector": 228,
      "credits": 997,
      "turns_executed": 12,
      "uptime_seconds": 0,
      "last_update_time": 1770521591.31631,
      "error_message": null
    },
    "bot_31_gameB_opp_t50_e2_b1": {
      "bot_id": "bot_31_gameB_opp_t50_e2_b1",
      "pid": 6464,
      "config": "config/test_matrix/31_gameB_opp_t50_e2_b1.yaml",
      "state": "completed",
      "sector": 0,
      "credits": 0,
      "turns_executed": 0,
      "uptime_seconds": 0,
      "last_update_time": 1770521483.830389,
      "error_message": null
    },
    "bot_32_gameB_opp_t50_e2_b0": {
      "bot_id": "bot_32_gameB_opp_t50_e2_b0",
      "pid": 6469,
      "config": "config/test_matrix/32_gameB_opp_t50_e2_b0.yaml",
      "state": "completed",
      "sector": 0,
      "credits": 0,
      "turns_executed": 0,
      "uptime_seconds": 0,
      "last_update_time": 1770521484.345664,
      "error_message": null
    },
    "bot_33_gameB_opp_t50_e5_b1": {
      "bot_id": "bot_33_gameB_opp_t50_e5_b1",
      "pid": 6474,
      "config": "config/test_matrix/33_gameB_opp_t50_e5_b1.yaml",
      "state": "completed",
      "sector": 0,
      "credits": 0,
      "turns_executed": 0,
      "uptime_seconds": 0,
      "last_update_time": 1770521484.285014,
      "error_message": null
    },
    "bot_34_gameB_opp_t50_e5_b0": {
      "bot_id": "bot_34_gameB_opp_t50_e5_b0",
      "pid": 6478,
      "config": "config/test_matrix/34_gameB_opp_t50_e5_b0.yaml",
      "state": "completed",
      "sector": 0,
      "credits": 0,
      "turns_executed": 0,
      "uptime_seconds": 0,
      "last_update_time": 1770521484.4612532,
      "error_message": null
    },
    "bot_35_gameB_opp_t50_e8_b1": {
      "bot_id": "bot_35_gameB_opp_t50_e8_b1",
      "pid": 6483,
      "config": "config/test_matrix/35_gameB_opp_t50_e8_b1.yaml",
      "state": "completed",
      "sector": 0,
      "credits": 0,
      "turns_executed": 0,
      "uptime_seconds": 0,
      "last_update_time": 1770521484.427336,
      "error_message": null
    },
    "bot_36_gameB_opp_t50_e8_b0": {
      "bot_id": "bot_36_gameB_opp_t50_e8_b0",
      "pid": 6488,
      "config": "config/test_matrix/36_gameB_opp_t50_e8_b0.yaml",
      "state": "completed",
      "sector": 0,
      "credits": 0,
      "turns_executed": 0,
      "uptime_seconds": 0,
      "last_update_time": 1770521484.492893,
      "error_message": null
    },
    "bot_37_gameC_opp_t15_e2_b1": {
      "bot_id": "bot_37_gameC_opp_t15_e2_b1",
      "pid": 6492,
      "config": "config/test_matrix/37_gameC_opp_t15_e2_b1.yaml",
      "state": "completed",
      "sector": 0,
      "credits": 0,
      "turns_executed": 0,
      "uptime_seconds": 0,
      "last_update_time": 1770521484.389058,
      "error_message": null
    },
    "bot_38_gameC_opp_t15_e2_b0": {
      "bot_id": "bot_38_gameC_opp_t15_e2_b0",
      "pid": 6496,
      "config": "config/test_matrix/38_gameC_opp_t15_e2_b0.yaml",
      "state": "completed",
      "sector": 0,
      "credits": 0,
      "turns_executed": 0,
      "uptime_seconds": 0,
      "last_update_time": 1770521484.52412,
      "error_message": null
    },
    "bot_39_gameC_opp_t15_e5_b1": {
      "bot_id": "bot_39_gameC_opp_t15_e5_b1",
      "pid": 6501,
      "config": "config/test_matrix/39_gameC_opp_t15_e5_b1.yaml",
      "state": "completed",
      "sector": 0,
      "credits": 0,
      "turns_executed": 0,
      "uptime_seconds": 0,
      "last_update_time": 1770521484.666079,
      "error_message": null
    },
    "bot_40_gameC_opp_t15_e5_b0": {
      "bot_id": "bot_40_gameC_opp_t15_e5_b0",
      "pid": 6505,
      "config": "config/test_matrix/40_gameC_opp_t15_e5_b0.yaml",
      "state": "completed",
      "sector": 0,
      "credits": 0,
      "turns_executed": 0,
      "uptime_seconds": 0,
      "last_update_time": 1770521484.631937,
      "error_message": null
    },
    "bot_41_gameC_opp_t15_e8_b1": {
      "bot_id": "bot_41_gameC_opp_t15_e8_b1",
      "pid": 6509,
      "config": "config/test_matrix/41_gameC_opp_t15_e8_b1.yaml",
      "state": "completed",
      "sector": 0,
      "credits": 0,
      "turns_executed": 0,
      "uptime_seconds": 0,
      "last_update_time": 1770521484.562282,
      "error_message": null
    },
    "bot_42_gameC_opp_t15_e8_b0": {
      "bot_id": "bot_42_gameC_opp_t15_e8_b0",
      "pid": 6513,
      "config": "config/test_matrix/42_gameC_opp_t15_e8_b0.yaml",
      "state": "completed",
      "sector": 0,
      "credits": 0,
      "turns_executed": 0,
      "uptime_seconds": 0,
      "last_update_time": 1770521513.887516,
      "error_message": null
    },
    "bot_43_gameC_opp_t30_e2_b1": {
      "bot_id": "bot_43_gameC_opp_t30_e2_b1",
      "pid": 6518,
      "config": "config/test_matrix/43_gameC_opp_t30_e2_b1.yaml",
      "state": "completed",
      "sector": 0,
      "credits": 0,
      "turns_executed": 0,
      "uptime_seconds": 0,
      "last_update_time": 1770521485.0118248,
      "error_message": null
    },
    "bot_44_gameC_opp_t30_e2_b0": {
      "bot_id": "bot_44_gameC_opp_t30_e2_b0",
      "pid": 6522,
      "config": "config/test_matrix/44_gameC_opp_t30_e2_b0.yaml",
      "state": "completed",
      "sector": 0,
      "credits": 0,
      "turns_executed": 0,
      "uptime_seconds": 0,
      "last_update_time": 1770521484.939779,
      "error_message": null
    },
    "bot_45_gameC_opp_t30_e5_b1": {
      "bot_id": "bot_45_gameC_opp_t30_e5_b1",
      "pid": 6526,
      "config": "config/test_matrix/45_gameC_opp_t30_e5_b1.yaml",
      "state": "completed",
      "sector": 0,
      "credits": 0,
      "turns_executed": 0,
      "uptime_seconds": 0,
      "last_update_time": 1770521485.069886,
      "error_message": null
    },
    "bot_46_gameC_opp_t30_e5_b0": {
      "bot_id": "bot_46_gameC_opp_t30_e5_b0",
      "pid": 6530,
      "config": "config/test_matrix/46_gameC_opp_t30_e5_b0.yaml",
      "state": "completed",
      "sector": 0,
      "credits": 0,
      "turns_executed": 0,
      "uptime_seconds": 0,
      "last_update_time": 1770521484.9806578,
      "error_message": null
    },
    "bot_47_gameC_opp_t30_e8_b1": {
      "bot_id": "bot_47_gameC_opp_t30_e8_b1",
      "pid": 6534,
      "config": "config/test_matrix/47_gameC_opp_t30_e8_b1.yaml",
      "state": "completed",
      "sector": 0,
      "credits": 0,
      "turns_executed": 0,
      "uptime_seconds": 0,
      "last_update_time": 1770521514.2058618,
      "error_message": null
    },
    "bot_48_gameC_opp_t30_e8_b0": {
      "bot_id": "bot_48_gameC_opp_t30_e8_b0",
      "pid": 6538,
      "config": "config/test_matrix/48_gameC_opp_t30_e8_b0.yaml",
      "state": "completed",
      "sector": 0,
      "credits": 0,
      "turns_executed": 0,
      "uptime_seconds": 0,
      "last_update_time": 1770521485.059795,
      "error_message": null
    },
    "bot_49_gameC_opp_t50_e2_b1": {
      "bot_id": "bot_49_gameC_opp_t50_e2_b1",
      "pid": 6547,
      "config": "config/test_matrix/49_gameC_opp_t50_e2_b1.yaml",
      "state": "completed",
      "sector": 0,
      "credits": 0,
      "turns_executed": 0,
      "uptime_seconds": 0,
      "last_update_time": 1770521485.067467,
      "error_message": null
    },
    "bot_50_gameC_opp_t50_e2_b0": {
      "bot_id": "bot_50_gameC_opp_t50_e2_b0",
      "pid": 6553,
      "config": "config/test_matrix/50_gameC_opp_t50_e2_b0.yaml",
      "state": "completed",
      "sector": 0,
      "credits": 0,
      "turns_executed": 0,
      "uptime_seconds": 0,
      "last_update_time": 1770521485.067084,
      "error_message": null
    },
    "bot_51_gameC_opp_t50_e5_b1": {
      "bot_id": "bot_51_gameC_opp_t50_e5_b1",
      "pid": 6558,
      "config": "config/test_matrix/51_gameC_opp_t50_e5_b1.yaml",
      "state": "completed",
      "sector": 0,
      "credits": 0,
      "turns_executed": 0,
      "uptime_seconds": 0,
      "last_update_time": 1770521514.4452832,
      "error_message": null
    },
    "bot_52_gameC_opp_t50_e5_b0": {
      "bot_id": "bot_52_gameC_opp_t50_e5_b0",
      "pid": 6562,
      "config": "config/test_matrix/52_gameC_opp_t50_e5_b0.yaml",
      "state": "completed",
      "sector": 0,
      "credits": 0,
      "turns_executed": 0,
      "uptime_seconds": 0,
      "last_update_time": 1770521485.1006389,
      "error_message": null
    },
    "bot_53_gameC_opp_t50_e8_b1": {
      "bot_id": "bot_53_gameC_opp_t50_e8_b1",
      "pid": 6566,
      "config": "config/test_matrix/53_gameC_opp_t50_e8_b1.yaml",
      "state": "completed",
      "sector": 0,
      "credits": 0,
      "turns_executed": 0,
      "uptime_seconds": 0,
      "last_update_time": 1770521485.8520179,
      "error_message": null
    },
    "bot_54_gameC_opp_t50_e8_b0": {
      "bot_id": "bot_54_gameC_opp_t50_e8_b0",
      "pid": 6570,
      "config": "config/test_matrix/54_gameC_opp_t50_e8_b0.yaml",
      "state": "completed",
      "sector": 0,
      "credits": 0,
      "turns_executed": 0,
      "uptime_seconds": 0,
      "last_update_time": 1770521483.8300412,
      "error_message": null
    },
    "bot_55_gameA_ai_t15_no_int_b1": {
      "bot_id": "bot_55_gameA_ai_t15_no_int_b1",
      "pid": 6574,
      "config": "config/test_matrix/55_gameA_ai_t15_no_int_b1.yaml",
      "state": "completed",
      "sector": 0,
      "credits": 0,
      "turns_executed": 0,
      "uptime_seconds": 0,
      "last_update_time": 1770521489.342013,
      "error_message": null
    },
    "bot_56_gameA_ai_t15_no_int_b0": {
      "bot_id": "bot_56_gameA_ai_t15_no_int_b0",
      "pid": 6578,
      "config": "config/test_matrix/56_gameA_ai_t15_no_int_b0.yaml",
      "state": "completed",
      "sector": 0,
      "credits": 0,
      "turns_executed": 0,
      "uptime_seconds": 0,
      "last_update_time": 1770521487.0867178,
      "error_message": null
    },
    "bot_57_gameA_ai_t15_int_auto0_b1": {
      "bot_id": "bot_57_gameA_ai_t15_int_auto0_b1",
      "pid": 6582,
      "config": "config/test_matrix/57_gameA_ai_t15_int_auto0_b1.yaml",
      "state": "completed",
      "sector": 0,
      "credits": 0,
      "turns_executed": 0,
      "uptime_seconds": 0,
      "last_update_time": 1770521487.121803,
      "error_message": null
    },
    "bot_58_gameA_ai_t15_int_auto0_b0": {
      "bot_id": "bot_58_gameA_ai_t15_int_auto0_b0",
      "pid": 6586,
      "config": "config/test_matrix/58_gameA_ai_t15_int_auto0_b0.yaml",
      "state": "completed",
      "sector": 0,
      "credits": 0,
      "turns_executed": 0,
      "uptime_seconds": 0,
      "last_update_time": 1770521482.033955,
      "error_message": null
    },
    "bot_59_gameA_ai_t15_int_auto1_b1": {
      "bot_id": "bot_59_gameA_ai_t15_int_auto1_b1",
      "pid": 6590,
      "config": "config/test_matrix/59_gameA_ai_t15_int_auto1_b1.yaml",
      "state": "completed",
      "sector": 0,
      "credits": 0,
      "turns_executed": 0,
      "uptime_seconds": 0,
      "last_update_time": 1770521489.344905,
      "error_message": null
    },
    "bot_60_gameA_ai_t15_int_auto1_b0": {
      "bot_id": "bot_60_gameA_ai_t15_int_auto1_b0",
      "pid": 6594,
      "config": "config/test_matrix/60_gameA_ai_t15_int_auto1_b0.yaml",
      "state": "completed",
      "sector": 0,
      "credits": 0,
      "turns_executed": 0,
      "uptime_seconds": 0,
      "last_update_time": 1770521485.3241951,
      "error_message": null
    },
    "bot_61_gameA_ai_t30_no_int_b1": {
      "bot_id": "bot_61_gameA_ai_t30_no_int_b1",
      "pid": 6598,
      "config": "config/test_matrix/61_gameA_ai_t30_no_int_b1.yaml",
      "state": "completed",
      "sector": 0,
      "credits": 0,
      "turns_executed": 0,
      "uptime_seconds": 0,
      "last_update_time": 1770521485.5967748,
      "error_message": null
    },
    "bot_62_gameA_ai_t30_no_int_b0": {
      "bot_id": "bot_62_gameA_ai_t30_no_int_b0",
      "pid": 6602,
      "config": "config/test_matrix/62_gameA_ai_t30_no_int_b0.yaml",
      "state": "completed",
      "sector": 0,
      "credits": 0,
      "turns_executed": 0,
      "uptime_seconds": 0,
      "last_update_time": 1770521483.6942458,
      "error_message": null
    },
    "bot_63_gameA_ai_t30_int_auto0_b1": {
      "bot_id": "bot_63_gameA_ai_t30_int_auto0_b1",
      "pid": 6606,
      "config": "config/test_matrix/63_gameA_ai_t30_int_auto0_b1.yaml",
      "state": "completed",
      "sector": 512,
      "credits": 0,
      "turns_executed": 1,
      "uptime_seconds": 0,
      "last_update_time": 1770521585.62422,
      "error_message": null
    },
    "bot_64_gameA_ai_t30_int_auto0_b0": {
      "bot_id": "bot_64_gameA_ai_t30_int_auto0_b0",
      "pid": 6610,
      "config": "config/test_matrix/64_gameA_ai_t30_int_auto0_b0.yaml",
      "state": "completed",
      "sector": 0,
      "credits": 0,
      "turns_executed": 0,
      "uptime_seconds": 0,
      "last_update_time": 1770521487.565456,
      "error_message": null
    },
    "bot_65_gameA_ai_t30_int_auto1_b1": {
      "bot_id": "bot_65_gameA_ai_t30_int_auto1_b1",
      "pid": 6614,
      "config": "config/test_matrix/65_gameA_ai_t30_int_auto1_b1.yaml",
      "state": "completed",
      "sector": 0,
      "credits": 0,
      "turns_executed": 0,
      "uptime_seconds": 0,
      "last_update_time": 1770521482.1921039,
      "error_message": null
    },
    "bot_66_gameA_ai_t30_int_auto1_b0": {
      "bot_id": "bot_66_gameA_ai_t30_int_auto1_b0",
      "pid": 6618,
      "config": "config/test_matrix/66_gameA_ai_t30_int_auto1_b0.yaml",
      "state": "completed",
      "sector": 0,
      "credits": 0,
      "turns_executed": 0,
      "uptime_seconds": 0,
      "last_update_time": 1770521482.192662,
      "error_message": null
    },
    "bot_67_gameA_ai_t50_no_int_b1": {
      "bot_id": "bot_67_gameA_ai_t50_no_int_b1",
      "pid": 6622,
      "config": "config/test_matrix/67_gameA_ai_t50_no_int_b1.yaml",
      "state": "completed",
      "sector": 0,
      "credits": 0,
      "turns_executed": 0,
      "uptime_seconds": 0,
      "last_update_time": 1770521482.218071,
      "error_message": null
    },
    "bot_68_gameA_ai_t50_no_int_b0": {
      "bot_id": "bot_68_gameA_ai_t50_no_int_b0",
      "pid": 6626,
      "config": "config/test_matrix/68_gameA_ai_t50_no_int_b0.yaml",
      "state": "completed",
      "sector": 0,
      "credits": 0,
      "turns_executed": 0,
      "uptime_seconds": 0,
      "last_update_time": 1770521482.2261918,
      "error_message": null
    },
    "bot_01_game_A_opportunistic": {
      "bot_id": "bot_01_game_A_opportunistic",
      "pid": 7863,
      "config": "config/test_matrix/01_game_A_opportunistic.yaml",
      "state": "stopped",
      "sector": 0,
      "credits": 0,
      "turns_executed": 0,
      "uptime_seconds": 0,
      "last_update_time": 1770521913.5142841,
      "error_message": null
    },
    "bot_01_gameA_opp_t15_e2_b1": {
      "bot_id": "bot_01_gameA_opp_t15_e2_b1",
      "pid": 7865,
      "config": "config/test_matrix/01_gameA_opp_t15_e2_b1.yaml",
      "state": "stopped",
      "sector": 698,
      "credits": 0,
      "turns_executed": 1,
      "uptime_seconds": 0,
      "last_update_time": 1770521938.201235,
      "error_message": null
    },
    "trader_01": {
      "bot_id": "trader_01",
      "pid": 8108,
      "config": "config/swarm_demo/bot_01.yaml",
      "state": "running",
      "sector": 836,
      "credits": 0,
      "turns_executed": 1,
      "uptime_seconds": 0,
      "last_update_time": 1770522054.5339,
      "error_message": null
    },
    "trader_02": {
      "bot_id": "trader_02",
      "pid": 8118,
      "config": "config/swarm_demo/bot_02.yaml",
      "state": "running",
      "sector": 836,
      "credits": 0,
      "turns_executed": 1,
      "uptime_seconds": 0,
      "last_update_time": 1770522064.112619,
      "error_message": null
    },
    "trader_03": {
      "bot_id": "trader_03",
      "pid": 8149,
      "config": "config/swarm_demo/bot_03.yaml",
      "state": "running",
      "sector": 836,
      "credits": 0,
      "turns_executed": 1,
      "uptime_seconds": 0,
      "last_update_time": 1770522069.339052,
      "error_message": null
    },
    "trader_04": {
      "bot_id": "trader_04",
      "pid": 8167,
      "config": "config/swarm_demo/bot_04.yaml",
      "state": "running",
      "sector": 836,
      "credits": 0,
      "turns_executed": 1,
      "uptime_seconds": 0,
      "last_update_time": 1770522073.994743,
      "error_message": null
    },
    "trader_05": {
      "bot_id": "trader_05",
      "pid": 8199,
      "config": "config/swarm_demo/bot_05.yaml",
      "state": "running",
      "sector": 836,
      "credits": 0,
      "turns_executed": 1,
      "uptime_seconds": 0,
      "last_update_time": 1770522079.480629,
      "error_message": null
    },
    "trader_06": {
      "bot_id": "trader_06",
      "pid": 10017,
      "config": "config/swarm_demo/bot_06.yaml",
      "state": "running",
      "sector": 836,
      "credits": 0,
      "turns_executed": 1,
      "uptime_seconds": 0,
      "last_update_time": 1770522083.929228,
      "error_message": null
    },
    "trader_07": {
      "bot_id": "trader_07",
      "pid": 11927,
      "config": "config/swarm_demo/bot_07.yaml",
      "state": "running",
      "sector": 836,
      "credits": 0,
      "turns_executed": 1,
      "uptime_seconds": 0,
      "last_update_time": 1770522089.1635258,
      "error_message": null
    },
    "trader_08": {
      "bot_id": "trader_08",
      "pid": 11944,
      "config": "config/swarm_demo/bot_08.yaml",
      "state": "running",
      "sector": 836,
      "credits": 0,
      "turns_executed": 1,
      "uptime_seconds": 0,
      "last_update_time": 1770522093.900673,
      "error_message": null
    },
    "trader_09": {
      "bot_id": "trader_09",
      "pid": 13023,
      "config": "config/swarm_demo/bot_09.yaml",
      "state": "running",
      "sector": 836,
      "credits": 0,
      "turns_executed": 1,
      "uptime_seconds": 0,
      "last_update_time": 1770522098.973571,
      "error_message": null
    },
    "trader_10": {
      "bot_id": "trader_10",
      "pid": 14214,
      "config": "config/swarm_demo/bot_10.yaml",
      "state": "running",
      "sector": 836,
      "credits": 0,
      "turns_executed": 1,
      "uptime_seconds": 0,
      "last_update_time": 1770522104.201938,
      "error_message": null
    },
    "trader_11": {
      "bot_id": "trader_11",
      "pid": 15275,
      "config": "config/swarm_demo/bot_11.yaml",
      "state": "running",
      "sector": 836,
      "credits": 0,
      "turns_executed": 1,
      "uptime_seconds": 0,
      "last_update_time": 1770522108.946082,
      "error_message": null
    },
    "trader_12": {
      "bot_id": "trader_12",
      "pid": 15297,
      "config": "config/swarm_demo/bot_12.yaml",
      "state": "running",
      "sector": 836,
      "credits": 0,
      "turns_executed": 1,
      "uptime_seconds": 0,
      "last_update_time": 1770522114.319351,
      "error_message": null
    },
    "trader_13": {
      "bot_id": "trader_13",
      "pid": 15444,
      "config": "config/swarm_demo/bot_13.yaml",
      "state": "running",
      "sector": 836,
      "credits": 0,
      "turns_executed": 1,
      "uptime_seconds": 0,
      "last_update_time": 1770522119.569058,
      "error_message": null
    },
    "trader_14": {
      "bot_id": "trader_14",
      "pid": 15471,
      "config": "config/swarm_demo/bot_14.yaml",
      "state": "running",
      "sector": 836,
      "credits": 0,
      "turns_executed": 1,
      "uptime_seconds": 0,
      "last_update_time": 1770522124.329976,
      "error_message": null
    },
    "trader_15": {
      "bot_id": "trader_15",
      "pid": 15550,
      "config": "config/swarm_demo/bot_15.yaml",
      "state": "running",
      "sector": 836,
      "credits": 0,
      "turns_executed": 1,
      "uptime_seconds": 0,
      "last_update_time": 1770522129.444722,
      "error_message": null
    },
    "trader_16": {
      "bot_id": "trader_16",
      "pid": 15572,
      "config": "config/swarm_demo/bot_16.yaml",
      "state": "running",
      "sector": 836,
      "credits": 0,
      "turns_executed": 1,
      "uptime_seconds": 0,
      "last_update_time": 1770522134.178464,
      "error_message": null
    },
    "trader_17": {
      "bot_id": "trader_17",
      "pid": 15588,
      "config": "config/swarm_demo/bot_17.yaml",
      "state": "running",
      "sector": 836,
      "credits": 0,
      "turns_executed": 1,
      "uptime_seconds": 0,
      "last_update_time": 1770522133.61697,
      "error_message": null
    },
    "trader_18": {
      "bot_id": "trader_18",
      "pid": 15603,
      "config": "config/swarm_demo/bot_18.yaml",
      "state": "running",
      "sector": 836,
      "credits": 2122,
      "turns_executed": 24,
      "uptime_seconds": 0,
      "last_update_time": 1770522167.129514,
      "error_message": null
    }
  }
}